_ioplace_parser_antlr/ioLexer.py
_ioplace_parser_antlr/ioListener.py
_ioplace_parser_antlr/ioParser.py
ioplace_parser/__init__.py
ioplace_parser/parse.py
ioplace_parser-0.3.0.dist-info/METADATA
ioplace_parser-0.3.0.dist-info/WHEEL
ioplace_parser-0.3.0.dist-info/RECORD
